jor/__init__.py
jor/jobs_base.py
jor-0.1.2.data/scripts/jor
jor-0.1.2.dist-info/LICENSE
jor-0.1.2.dist-info/METADATA
jor-0.1.2.dist-info/WHEEL
jor-0.1.2.dist-info/top_level.txt
jor-0.1.2.dist-info/zip-safe
jor-0.1.2.dist-info/RECORD
