Metadata-Version: 2.1
Name: jor
Version: 0.1.2
Summary: Lighweight JOb Runner for reproducible research results in HPC environments
Home-page: https://github.com/mdhelmer/jor
Author: Markus Helmer
License: GPLv3
Platform: UNKNOWN
Classifier: Development Status :: 4 - Beta
Classifier: License :: OSI Approved :: GNU General Public License v3 (GPLv3)
Classifier: Programming Language :: Python :: 3.6
Classifier: Programming Language :: Python :: 3.7
Classifier: Programming Language :: Python :: 3.8
Classifier: Topic :: Scientific/Engineering
Classifier: Intended Audience :: Science/Research
Requires-Python: >=3.6
